pix/__init__.py
pix/pix.py
pix_engine-0.1.0.dist-info/METADATA
pix_engine-0.1.0.dist-info/WHEEL
pix_engine-0.1.0.dist-info/licenses/LICENSE
pix_engine-0.1.0.dist-info/RECORD
