Metadata-Version: 2.1
Name: PIX-engine
Version: 0.1.0
Summary: Terminal game engine that is community supported and open source
Project-URL: Homepage, https://github.com/TVRework/PIX
Project-URL: Bug Tracker, https://github.com/TVRework/PIX/issues
Author-email: TVRework <boxeigit@gmail.com>
License-File: LICENSE
Classifier: License :: OSI Approved :: MIT License
Classifier: Operating System :: OS Independent
Classifier: Programming Language :: Python :: 3
Requires-Python: >=3.7
